{
  "id": "1431095e-05fd-47b6-87a3-1017fc694453",
  "prevId": "00000000-0000-0000-0000-000000000000",
  "version": "5",
  "dialect": "pg",
  "tables": {
    "users": {
      "name": "users",
      "schema": "",
      "columns": {
        "id": {
          "name": "id",
          "type": "serial",
          "primaryKey": true,
          "notNull": true
        },
        "full_name": {
          "name": "full_name",
          "type": "text",
          "primaryKey": false,
          "notNull": true
        },
        "phone": {
          "name": "phone",
          "type": "varchar(256)",
          "primaryKey": false,
          "notNull": true
        },
        "username": {
          "name": "username",
          "type": "varchar(256)",
          "primaryKey": false,
          "notNull": true
        },
        "email": {
          "name": "email",
          "type": "varchar(256)",
          "primaryKey": false,
          "notNull": true
        },
        "password": {
          "name": "password",
          "type": "varchar(256)",
          "primaryKey": false,
          "notNull": true
        }
      },
      "indexes": {},
      "foreignKeys": {},
      "compositePrimaryKeys": {},
      "uniqueConstraints": {}
    }
  },
  "enums": {},
  "schemas": {},
  "_meta": {
    "schemas": {},
    "tables": {},
    "columns": {}
  }
}